__init__.py
__main__.py
http_file_reader/__init__.py
http_file_reader/http_file_reader.py
split_file_reader/__init__.py
split_file_reader/__main__.py
split_file_reader/split_file_reader.py
split_file_reader/http_file_reader/__init__.py
split_file_reader/http_file_reader/http_file_reader.py
split_file_reader/split_file_reader/__init__.py
split_file_reader/split_file_reader/__main__.py
split_file_reader/split_file_reader/split_file_reader.py
split_file_reader/split_file_writer/__init__.py
split_file_reader/split_file_writer/split_file_writer.py
split_file_writer/__init__.py
split_file_writer/split_file_writer.py
split_file_reader-0.1.4.dist-info/LICENSE
split_file_reader-0.1.4.dist-info/METADATA
split_file_reader-0.1.4.dist-info/WHEEL
split_file_reader-0.1.4.dist-info/entry_points.txt
split_file_reader-0.1.4.dist-info/top_level.txt
split_file_reader-0.1.4.dist-info/RECORD
